LICENSE
README.md
setup.cfg
setup.py
autocut/__init__.py
autocut/__main__.py
autocut/cut.py
autocut/daemon.py
autocut/main.py
autocut/transcribe.py
autocut/utils.py
autocut_fix.egg-info/PKG-INFO
autocut_fix.egg-info/SOURCES.txt
autocut_fix.egg-info/dependency_links.txt
autocut_fix.egg-info/entry_points.txt
autocut_fix.egg-info/requires.txt
autocut_fix.egg-info/top_level.txt
test/test_cut.py
test/test_transcribe.py