Metadata-Version: 2.1
Name: autocut-fix
Version: 0.0.1
Summary: Cut the video by subtitle. This project changes the whisper dependency of the original project to openai-whisper.
License: Apache Software License
Classifier: License :: OSI Approved :: Apache Software License
Classifier: Operating System :: OS Independent
Classifier: Programming Language :: Python :: 3
Requires-Python: >=3.9
License-File: LICENSE
